dcel/__init__.py
dcel/dcel.py
dcel/point.py
dcel/primitives.py
dcel/utils.py
dcel/vertex.py
pydcel-1.0.3.dist-info/METADATA
pydcel-1.0.3.dist-info/WHEEL
pydcel-1.0.3.dist-info/RECORD
